LICENSE
README.md
setup.py
printstructure/__init__.py
printstructure/lib.py
printstructure/printdp.py
printstructure/printtree.py
printstructure.egg-info/PKG-INFO
printstructure.egg-info/SOURCES.txt
printstructure.egg-info/dependency_links.txt
printstructure.egg-info/requires.txt
printstructure.egg-info/top_level.txt