Metadata-Version: 2.1
Name: printstructure
Version: 0.1.1
Summary: A Python library that can elegantly print out complex data structures
Home-page: https://github.com/DavidHo666/print-structure
Author: Dawei He
License-File: LICENSE
